py_text_clock/__init__.py
py_text_clock/clockFace.py
py_text_clock/command_line.py
py_text_clock/fontMods.py
py_text_clock/mylogger.py
py_text_clock-0.3.5.dist-info/METADATA
py_text_clock-0.3.5.dist-info/WHEEL
py_text_clock-0.3.5.dist-info/entry_points.txt
py_text_clock-0.3.5.dist-info/RECORD
