Metadata-Version: 2.1
Name: py-text-clock
Version: 0.3.5
Summary: A verbose Clock
Author: Manoj Manivannan
Author-email: manojm18@live.in
Requires-Python: >=3.11,<4.0
Classifier: Programming Language :: Python :: 3
Classifier: Programming Language :: Python :: 3.11
Classifier: Programming Language :: Python :: 3.12
Classifier: Programming Language :: Python :: 3.13
Requires-Dist: click (>=8.1.7,<9.0.0)
Requires-Dist: pytest (>=7.4.0,<8.0.0)
